tap_krow/__init__.py
tap_krow/auth.py
tap_krow/client.py
tap_krow/normalize.py
tap_krow/streams.py
tap_krow/tap.py
tap_krow/tests/__init__.py
tap_krow/tests/api_responses/applicants/applicants_default.json
tap_krow/tests/api_responses/campaigns/campaigns_no_relationships_property.json
tap_krow/tests/api_responses/campaigns/campaigns_zero_records.json
tap_krow/tests/api_responses/locations/locations_default.json
tap_krow/tests/api_responses/organizations/orgs_default.json
tap_krow/tests/api_responses/organizations/orgs_last_page.json
tap_krow/tests/api_responses/organizations/orgs_records_before_and_after_2020-01-01.json
tap_krow/tests/api_responses/positions/positions_default.json
tap_krow/tests/api_responses/regions/regions_default.json
tap_krow/tests/test_applicants_stream.py
tap_krow/tests/test_client.py
tap_krow/tests/test_core.py
tap_krow/tests/test_locations_stream.py
tap_krow/tests/test_normalize.py
tap_krow/tests/test_organizations_stream.py
tap_krow/tests/test_paginator.py
tap_krow/tests/test_positions_stream.py
tap_krow/tests/test_regions_stream.py
tap_krow-0.10.3.dist-info/METADATA
tap_krow-0.10.3.dist-info/WHEEL
tap_krow-0.10.3.dist-info/entry_points.txt
tap_krow-0.10.3.dist-info/RECORD
