Metadata-Version: 2.1
Name: tap-krow
Version: 0.10.3
Summary: `tap-krow` is a Singer tap for the KROW API, built with the Meltano SDK for Singer Taps.
License: Apache 2.0
Author: Datateer
Requires-Python: >=3.7.1,<3.12
Classifier: License :: Other/Proprietary License
Classifier: Programming Language :: Python :: 3
Classifier: Programming Language :: Python :: 3.8
Classifier: Programming Language :: Python :: 3.9
Classifier: Programming Language :: Python :: 3.10
Classifier: Programming Language :: Python :: 3.11
Requires-Dist: requests (>=2.25.1,<3.0.0)
Requires-Dist: singer-sdk (>=0.22.0,<0.23.0)
